modularyze/__init__.py
modularyze/construct.py
modularyze/modularyze.py
modularyze/utils.py
modularyze-0.1.0.dist-info/LICENSE
modularyze-0.1.0.dist-info/WHEEL
modularyze-0.1.0.dist-info/METADATA
modularyze-0.1.0.dist-info/RECORD
