Metadata-Version: 2.1
Name: modularyze
Version: 0.1.0
Summary: Top-level package for modularyze.
Home-page: https://github.com/jungerm2/modularyze
License: GPL-3.0-only
Author: Sacha Jungerman
Author-email: jungerm2@illinois.edu
Requires-Python: >=3.6,<4.0
Classifier: Development Status :: 2 - Pre-Alpha
Classifier: Intended Audience :: Developers
Classifier: License :: OSI Approved :: GNU General Public License v3 (GPLv3)
Classifier: Natural Language :: English
Classifier: Programming Language :: Python :: 3
Classifier: Programming Language :: Python :: 3.6
Classifier: Programming Language :: Python :: 3.7
Classifier: Programming Language :: Python :: 3.8
Classifier: Programming Language :: Python :: 3.9
Requires-Dist: Jinja2 (>=2.11.2,<3.0.0)
Requires-Dist: ruamel.yaml (>=0.16.12,<0.17.0)
